ldaptools/__init__.py
ldaptools/exceptions.py
ldaptools/ldap_source.py
ldaptools/ldif_utils.py
ldaptools/paged.py
ldaptools/slapd.py
ldaptools/synchronize.py
ldaptools/utils.py
ldaptools/ldapsync/__init__.py
ldaptools/ldapsync/cmd.py
ldaptools/schemas/core.ldif
ldaptools/schemas/cosine.ldif
ldaptools/schemas/eduorg-200210-openldap.ldif
ldaptools/schemas/eduperson.ldif
ldaptools/schemas/inetorgperson.ldif
ldaptools/schemas/nis.ldif
ldaptools/schemas/supann-2009.ldif
ldaptools-0.24.dist-info/METADATA
ldaptools-0.24.dist-info/WHEEL
ldaptools-0.24.dist-info/entry_points.txt
ldaptools-0.24.dist-info/top_level.txt
ldaptools-0.24.dist-info/RECORD
