Metadata-Version: 2.1
Name: ldaptools
Version: 0.24
Summary: ldaptools
Home-page: http://dev.entrouvert.org/projects/ldaptools/
Author: Entr'ouvert
Author-email: authentic@listes.entrouvert.com
Maintainer: Benjamin Dauvergne
Maintainer-email: bdauvergne@entrouvert.com
License: AGPLv3+
Platform: UNKNOWN
Classifier: License :: OSI Approved :: MIT License
Classifier: Topic :: System :: Systems Administration :: Authentication/Directory
Classifier: Programming Language :: Python
Requires-Dist: python-ldap
Requires-Dist: six
